SferumAPI/__init__.py
SferumAPI/sferum_api.py
SferumAPI/calls/__init__.py
SferumAPI/calls/call_service.py
SferumAPI/calls/call_strategy.py
SferumAPI/calls/group_call.py
SferumAPI/calls/peer_call.py
SferumAPI/channels/__init__.py
SferumAPI/channels/channel_service.py
SferumAPI/messages/__init__.py
SferumAPI/messages/mesage_service.py
SferumAPI/models/__init__.py
SferumAPI/models/response.py
SferumAPI/models/calls/__init__.py
SferumAPI/models/calls/calls.py
SferumAPI/models/channels/__init__.py
SferumAPI/models/channels/channel_history.py
SferumAPI/models/messages/__init__.py
SferumAPI/models/messages/message.py
SferumAPI/models/messages/messages_history.py
SferumAPI/models/users/__init__.py
SferumAPI/models/users/anon.py
SferumAPI/models/users/user.py
SferumAPI/users/__init__.py
SferumAPI/users/anon_auth.py
SferumAPI/users/auth_strategy.py
SferumAPI/users/user_auth.py
SferumAPI/users/user_service.py
SferumAPI-0.1.1.dist-info/LICENSE
SferumAPI-0.1.1.dist-info/METADATA
SferumAPI-0.1.1.dist-info/WHEEL
SferumAPI-0.1.1.dist-info/top_level.txt
SferumAPI-0.1.1.dist-info/RECORD
