Metadata-Version: 2.1
Name: SferumAPI
Version: 0.1.1
Summary: API wrapper for Sferum platform
Home-page: https://github.com/l2700l/SferumAPI
Author: l2700l
Author-email: thetypgame@gmail.com
Classifier: Programming Language :: Python :: 3
Classifier: License :: OSI Approved :: MIT License
Classifier: Operating System :: OS Independent
Requires-Python: >=3.7
License-File: LICENSE
Requires-Dist: requests>=2.20.0
Requires-Dist: websockets>=10.0
